coccigrep/__init__.py
coccigrep/coccigrep.cfg
coccigrep/coccigrep.py
coccigrep/data/deref.cocci
coccigrep/data/func.cocci
coccigrep/data/named.cocci
coccigrep/data/set.cocci
coccigrep/data/test.cocci
coccigrep/data/used.cocci
coccigrep-1.21.data/scripts/coccigrep
coccigrep-1.21.dist-info/LICENSE
coccigrep-1.21.dist-info/METADATA
coccigrep-1.21.dist-info/WHEEL
coccigrep-1.21.dist-info/top_level.txt
coccigrep-1.21.dist-info/RECORD
