Metadata-Version: 2.1
Name: coccigrep
Version: 1.21
Summary: Semantic grep for C based on coccinelle
Home-page: http://home.regit.org/software/coccigrep/
Author: Eric Leblond
Author-email: eric@regit.org
Classifier: Development Status :: 5 - Production/Stable
Classifier: Environment :: Console
Classifier: Intended Audience :: Developers
Classifier: License :: OSI Approved :: GNU General Public License (GPL)
Classifier: Operating System :: POSIX
Classifier: Programming Language :: Python
Classifier: Topic :: Software Development
Provides: coccigrep
License-File: LICENSE
Requires-Dist: argparse
Requires-Dist: configparser
Requires-Dist: pygments
